setup.py
digILPRankings.egg-info/PKG-INFO
digILPRankings.egg-info/SOURCES.txt
digILPRankings.egg-info/dependency_links.txt
digILPRankings.egg-info/requires.txt
digILPRankings.egg-info/top_level.txt
digIlpRankings/__init__.py
digIlpRankings/ilp_extractions.py
digIlpRankings/setup.py