Metadata-Version: 1.1
Name: digILPRankings
Version: 0.3.10
Summary: digILPRankings
Home-page: https://github.com/usc-isi-i2/dig-ilp-rankings
Author: Rahul Kapoor
Author-email: rahulkap@isi.edu
License: UNKNOWN
Download-URL: https://github.com/usc-isi-i2/dig-ilp-rankings
Platform: UNKNOWN
